invertedai_drive/__init__.py
invertedai_drive/drive.py
invertedai_drive/models.py
invertedai_drive/requirements.txt
invertedai_drive/utils.py
invertedai_drive-0.1.3.dist-info/WHEEL
invertedai_drive-0.1.3.dist-info/METADATA
invertedai_drive-0.1.3.dist-info/RECORD
