Metadata-Version: 2.1
Name: invertedai-drive
Version: 0.1.3
Summary: Client SDK for InvertedAI Drive
License: MIT
Author: Inverted AI
Author-email: info@inverted.ai
Requires-Python: >=3.7.1,<3.11
Classifier: License :: OSI Approved :: MIT License
Classifier: Programming Language :: Python :: 3
Classifier: Programming Language :: Python :: 3.10
Classifier: Programming Language :: Python :: 3.8
Classifier: Programming Language :: Python :: 3.9
Requires-Dist: numpy (==1.21.2)
Requires-Dist: python-dotenv (>=0.20.0,<0.21.0)
Requires-Dist: torch (>=1.11.0,<2.0.0)
